xhs/__init__.py
xhs/__version__.py
xhs/core.py
xhs/exception.py
xhs/help.py
xhs-0.2.12.dist-info/LICENSE
xhs-0.2.12.dist-info/METADATA
xhs-0.2.12.dist-info/WHEEL
xhs-0.2.12.dist-info/top_level.txt
xhs-0.2.12.dist-info/RECORD
