Metadata-Version: 2.1
Name: xhs
Version: 0.2.12
Summary: xiaohongshu crawl sdk.
Home-page: https://github.com/ReaJason/xhs
Author: ReaJason
Author-email: reajason1225@gmail.com
License: MIT
Keywords: xhs crawl
Classifier: Development Status :: 3 - Alpha
Classifier: Intended Audience :: Developers
Classifier: License :: OSI Approved :: MIT License
Classifier: Programming Language :: Python
Classifier: Programming Language :: Python :: 3.8
Classifier: Programming Language :: Python :: 3.9
Classifier: Programming Language :: Python :: 3.10
Classifier: Programming Language :: Python :: 3.11
Classifier: Programming Language :: Python :: 3 :: Only
Classifier: Topic :: Software Development :: Libraries :: Python Modules
Requires-Python: >=3.7
License-File: LICENSE
Requires-Dist: requests
Requires-Dist: lxml
